py2snes/__init__.py
py2snes-0.3.0.dist-info/METADATA
py2snes-0.3.0.dist-info/WHEEL
py2snes-0.3.0.dist-info/top_level.txt
py2snes-0.3.0.dist-info/RECORD
