Metadata-Version: 2.1
Name: py2snes
Version: 0.3.0
Summary: A python module for interacting with the sd2snes using the usb2snes firmware by Redguyyyy.
Home-page: https://github.com/tcprescott/py2snes
Author: Thomas Prescott
Author-email: tcprescott@gmail.com
License: UNKNOWN
Platform: UNKNOWN
Classifier: Programming Language :: Python :: 3
Classifier: Programming Language :: Python :: 3.6
Classifier: License :: OSI Approved :: Apache Software License
Classifier: Operating System :: OS Independent
Requires-Dist: websocket-client
